yeelib/__init__.py
yeelib/devices.py
yeelib/discover.py
yeelib/exceptions.py
yeelib-2.1.10.dist-info/AUTHORS
yeelib-2.1.10.dist-info/LICENSE
yeelib-2.1.10.dist-info/METADATA
yeelib-2.1.10.dist-info/WHEEL
yeelib-2.1.10.dist-info/pbr.json
yeelib-2.1.10.dist-info/top_level.txt
yeelib-2.1.10.dist-info/RECORD
