Metadata-Version: 2.1
Name: yeelib
Version: 2.1.10
Summary: Python library for Xiaomi Mi Yeelight.
Home-page: https://github.com/codingjoe/yeelib
Author: Johannes Hoppe
Author-email: info@johanneshoppe.com
License: Apache-2
Keywords: light
Requires-Dist: ssdp (>=1.0.1)
